gateway_provisioners/__init__.py
gateway_provisioners/_version.py
gateway_provisioners/config_mixin.py
gateway_provisioners/container.py
gateway_provisioners/crd.py
gateway_provisioners/distributed.py
gateway_provisioners/docker_swarm.py
gateway_provisioners/k8s.py
gateway_provisioners/remote_provisioner.py
gateway_provisioners/response_manager.py
gateway_provisioners/spark_operator.py
gateway_provisioners/yarn.py
gateway_provisioners/app-support/README.md
gateway_provisioners/app-support/docker/Dockerfile
gateway_provisioners/app-support/docker/start-application.sh
gateway_provisioners/app-support/kubernetes/helm/gateway-provisioners/Chart.yaml
gateway_provisioners/app-support/kubernetes/helm/gateway-provisioners/values.yaml
gateway_provisioners/app-support/kubernetes/helm/gateway-provisioners/templates/daemonset.yaml
gateway_provisioners/app-support/kubernetes/helm/gateway-provisioners/templates/deployment.yaml
gateway_provisioners/app-support/kubernetes/helm/gateway-provisioners/templates/gp-clusterrole.yaml
gateway_provisioners/app-support/kubernetes/helm/gateway-provisioners/templates/gp-clusterrolebinding.yaml
gateway_provisioners/app-support/kubernetes/helm/gateway-provisioners/templates/gp-serviceaccount.yaml
gateway_provisioners/app-support/kubernetes/helm/gateway-provisioners/templates/imagepullSecret.yaml
gateway_provisioners/app-support/kubernetes/helm/gateway-provisioners/templates/ingress.yaml
gateway_provisioners/app-support/kubernetes/helm/gateway-provisioners/templates/kip-clusterrole.yaml
gateway_provisioners/app-support/kubernetes/helm/gateway-provisioners/templates/kip-clusterrolebinding.yaml
gateway_provisioners/app-support/kubernetes/helm/gateway-provisioners/templates/kip-serviceaccount.yaml
gateway_provisioners/app-support/kubernetes/helm/gateway-provisioners/templates/psp.yaml
gateway_provisioners/app-support/kubernetes/helm/gateway-provisioners/templates/service.yaml
gateway_provisioners/cli/__init__.py
gateway_provisioners/cli/base_app.py
gateway_provisioners-0.4.0.dist-info/METADATA
gateway_provisioners-0.4.0.dist-info/WHEEL
gateway_provisioners-0.4.0.dist-info/entry_points.txt
gateway_provisioners-0.4.0.dist-info/licenses/LICENSE.md
gateway_provisioners-0.4.0.dist-info/RECORD
