Metadata-Version: 2.3
Name: gateway_provisioners
Version: 0.4.0
Summary: Gateway Provisioners - a package containing kernel provisioners supporting the deployment of remote and resource-managed kernels.
Project-URL: Homepage, https://jupyter.org
Project-URL: Documentation, https://gateway-provisioners.readthedocs.io/
Project-URL: Source, https://github.com/jupyter-server/gateway_provisioners
Project-URL: Tracker, https://github.com/jupyter-server/gateway_provisioners/issues
Author-email: Jupyter Development Team <jupyter@googlegroups.org>
License: # Licensing terms
License-File: LICENSE.md
Classifier: Framework :: Jupyter
Classifier: Intended Audience :: Developers
Classifier: Intended Audience :: Science/Research
Classifier: Intended Audience :: System Administrators
Classifier: License :: OSI Approved :: BSD License
Classifier: Programming Language :: Python
Classifier: Programming Language :: Python :: 3
Requires-Python: >=3.8
Requires-Dist: jupyter-client>=7.4
Requires-Dist: overrides
Requires-Dist: paramiko>=2.4.0
Requires-Dist: pexpect>=4.2.0
Requires-Dist: pycryptodomex>=3.9.7
Requires-Dist: tornado>=6.2
Requires-Dist: traitlets>=5.1
Provides-Extra: dev
Requires-Dist: build; extra == 'dev'
Requires-Dist: coverage; extra == 'dev'
Requires-Dist: pre-commit; extra == 'dev'
Requires-Dist: twine; extra == 'dev'
Provides-Extra: docker
Requires-Dist: docker>=3.5.0; extra == 'docker'
Provides-Extra: docs
Requires-Dist: docker>=3.5.0; extra == 'docs'
Requires-Dist: docutils<0.21; extra == 'docs'
Requires-Dist: jinja2>=3.1; extra == 'docs'
Requires-Dist: kubernetes>=18.20.0; extra == 'docs'
Requires-Dist: mistune<4.0.0; extra == 'docs'
Requires-Dist: myst-parser; extra == 'docs'
Requires-Dist: pillow==9.5.0; extra == 'docs'
Requires-Dist: pydata-sphinx-theme; extra == 'docs'
Requires-Dist: sphinx-autodoc-typehints; extra == 'docs'
Requires-Dist: sphinx-copybutton; extra == 'docs'
Requires-Dist: sphinxcontrib-blockdiag; extra == 'docs'
Requires-Dist: sphinxcontrib-github-alt; extra == 'docs'
Requires-Dist: sphinxcontrib-openapi; extra == 'docs'
Requires-Dist: sphinxcontrib-seqdiag; extra == 'docs'
Requires-Dist: sphinxcontrib-spelling; extra == 'docs'
Requires-Dist: sphinxemoji; extra == 'docs'
Requires-Dist: tornado; extra == 'docs'
Requires-Dist: yarn-api-client; extra == 'docs'
Provides-Extra: k8s
Requires-Dist: jinja2>=3.1; extra == 'k8s'
Requires-Dist: kubernetes>=18.20.0; extra == 'k8s'
Provides-Extra: lint
Requires-Dist: black[jupyter]==23.11.0; extra == 'lint'
Requires-Dist: mdformat>0.7; extra == 'lint'
Requires-Dist: ruff==0.0.287; extra == 'lint'
Provides-Extra: test
Requires-Dist: docker>=3.5.0; extra == 'test'
Requires-Dist: importlib-metadata; extra == 'test'
Requires-Dist: jinja2>=3.1; extra == 'test'
Requires-Dist: kubernetes>=18.20.0; extra == 'test'
Requires-Dist: mock; extra == 'test'
Requires-Dist: pre-commit; extra == 'test'
Requires-Dist: pytest; extra == 'test'
Requires-Dist: pytest-cov; extra == 'test'
Requires-Dist: pytest-jupyter[server]>=0.4; extra == 'test'
Requires-Dist: pytest-timeout; extra == 'test'
Requires-Dist: pytest-tornasync; extra == 'test'
Requires-Dist: yarn-api-client; extra == 'test'
Provides-Extra: yarn
Requires-Dist: yarn-api-client; extra == 'yarn'
